setup.py
car_package/__init__.py
car_package.egg-info/PKG-INFO
car_package.egg-info/SOURCES.txt
car_package.egg-info/dependency_links.txt
car_package.egg-info/not-zip-safe
car_package.egg-info/top_level.txt