Metadata-Version: 1.0
Name: car-package
Version: 0.1
Summary: Start your car and drive off in it
Home-page: UNKNOWN
Author: Peter Begle
Author-email: p_begle@u.pacific.edu
License: MIT
Platform: UNKNOWN
